README.md
setup.cfg
setup.py
LAC/__init__.py
LAC/_compat.py
LAC/ahocorasick.py
LAC/cmdline.py
LAC/custom.py
LAC/lac.py
LAC/models.py
LAC/nets.py
LAC/prefix_tree.py
LAC/reader.py
LAC/segment.py
LAC/utils.py
LAC.egg-info/PKG-INFO
LAC.egg-info/SOURCES.txt
LAC.egg-info/dependency_links.txt
LAC.egg-info/entry_points.txt
LAC.egg-info/not-zip-safe
LAC.egg-info/top_level.txt
LAC/lac_model/conf/args.ini
LAC/lac_model/conf/q2b.dic
LAC/lac_model/conf/small_seg.dic
LAC/lac_model/conf/tag.dic
LAC/lac_model/conf/word.dic
LAC/lac_model/model/__model__
LAC/lac_model/model/crfw
LAC/lac_model/model/fc_0.b_0
LAC/lac_model/model/fc_0.w_0
LAC/lac_model/model/fc_1.b_0
LAC/lac_model/model/fc_1.w_0
LAC/lac_model/model/fc_2.b_0
LAC/lac_model/model/fc_2.w_0
LAC/lac_model/model/fc_3.b_0
LAC/lac_model/model/fc_3.w_0
LAC/lac_model/model/fc_4.b_0
LAC/lac_model/model/fc_4.w_0
LAC/lac_model/model/gru_0.b_0
LAC/lac_model/model/gru_0.w_0
LAC/lac_model/model/gru_1.b_0
LAC/lac_model/model/gru_1.w_0
LAC/lac_model/model/gru_2.b_0
LAC/lac_model/model/gru_2.w_0
LAC/lac_model/model/gru_3.b_0
LAC/lac_model/model/gru_3.w_0
LAC/lac_model/model/word_emb
LAC/rank_model/conf/args.ini
LAC/rank_model/conf/q2b.dic
LAC/rank_model/conf/small_seg.dic
LAC/rank_model/conf/tag.dic
LAC/rank_model/conf/word.dic
LAC/rank_model/model/__model__
LAC/rank_model/model/embedding_1.w_0
LAC/rank_model/model/fc_0.b_0
LAC/rank_model/model/fc_0.w_0
LAC/rank_model/model/fc_1.b_0
LAC/rank_model/model/fc_1.w_0
LAC/rank_model/model/fc_2.b_0
LAC/rank_model/model/fc_2.w_0
LAC/rank_model/model/fc_3.b_0
LAC/rank_model/model/fc_3.w_0
LAC/rank_model/model/lstm_0.b_0
LAC/rank_model/model/lstm_0.w_0
LAC/rank_model/model/lstm_1.b_0
LAC/rank_model/model/lstm_1.w_0
LAC/rank_model/model/word_emb
LAC/seg_model/conf/args.ini
LAC/seg_model/conf/q2b.dic
LAC/seg_model/conf/small_seg.dic
LAC/seg_model/conf/tag.dic
LAC/seg_model/conf/word.dic
LAC/seg_model/model/__model__
LAC/seg_model/model/crfw
LAC/seg_model/model/fc_0.b_0
LAC/seg_model/model/fc_0.w_0
LAC/seg_model/model/fc_1.b_0
LAC/seg_model/model/fc_1.w_0
LAC/seg_model/model/fc_2.b_0
LAC/seg_model/model/fc_2.w_0
LAC/seg_model/model/fc_3.b_0
