Metadata-Version: 2.1
Name: LAC
Version: 2.1.2
Summary: A chinese lexical analysis tool by Baidu NLP.
Home-page: https://github.com/baidu/lac
Author: Baidu NLP
Author-email: nlp-fenci@baidu.com
License: Apache 2.0
Keywords: lac chinese lexical analysis
Platform: any
Classifier: License :: OSI Approved :: Apache Software License
Classifier: Programming Language :: Python
Classifier: Programming Language :: Python :: 2
Classifier: Programming Language :: Python :: 2.7
Classifier: Programming Language :: Python :: 3
Classifier: Programming Language :: Python :: 3.5
Classifier: Programming Language :: Python :: 3.6
Classifier: Programming Language :: Python :: 3.7
